gradio_magicquill/__init__.py
gradio_magicquill/magicquill.py
gradio_magicquill/magicquill.pyi
gradio_magicquill/templates/component/index.js
gradio_magicquill/templates/component/style.css
gradio_magicquill/templates/example/index.js
gradio_magicquill-0.0.1.dist-info/METADATA
gradio_magicquill-0.0.1.dist-info/WHEEL
gradio_magicquill-0.0.1.dist-info/RECORD
