Metadata-Version: 2.3
Name: gradio_magicquill
Version: 0.0.1
Summary: Gradio library for the interface of MagicQuill, an intelligent interactive image editing system
Author-email: Yue Yu <yue.yu@connect.ust.hk>
License: Apache-2.0
Keywords: gradio-custom-component,image editing,magicquill
Classifier: Development Status :: 3 - Alpha
Classifier: Operating System :: OS Independent
Classifier: Programming Language :: Python :: 3
Classifier: Programming Language :: Python :: 3 :: Only
Classifier: Programming Language :: Python :: 3.8
Classifier: Programming Language :: Python :: 3.9
Classifier: Programming Language :: Python :: 3.10
Classifier: Programming Language :: Python :: 3.11
Classifier: Topic :: Scientific/Engineering
Classifier: Topic :: Scientific/Engineering :: Artificial Intelligence
Classifier: Topic :: Scientific/Engineering :: Visualization
Requires-Python: >=3.8
Requires-Dist: gradio==4.44.1
Provides-Extra: dev
Requires-Dist: build; extra == 'dev'
Requires-Dist: twine; extra == 'dev'
